<annotation>
  <folder>JPEGImages</folder>
  <filename>0776</filename>
  <path>H:\labelImg-master\windows_v1.2.2\data\voc\VOCdevkit\VOC2019\JPEGImages\0776.jpg</path>
  <source>
    <database>Unknown</database>
  </source>
  <size>
    <width>507</width>
    <height>266</height>
    <depth>3</depth>
  </size>
  <segmented>0</segmented>
  <object>
    <name>&#31908;</name>
    <pose>Unspecified</pose>
    <truncated>0</truncated>
    <difficult>0</difficult>
    <bndbox>
      <xmin>184</xmin>
      <ymin>194</ymin>
      <xmax>203</xmax>
      <ymax>229</ymax>
    </bndbox>
  </object>
  <object>
    <name>A</name>
    <pose>Unspecified</pose>
    <truncated>0</truncated>
    <difficult>0</difficult>
    <bndbox>
      <xmin>203</xmin>
      <ymin>194</ymin>
      <xmax>222</xmax>
      <ymax>229</ymax>
    </bndbox>
  </object>
  <object>
    <name>6</name>
    <pose>Unspecified</pose>
    <truncated>0</truncated>
    <difficult>0</difficult>
    <bndbox>
      <xmin>228</xmin>
      <ymin>194</ymin>
      <xmax>247</xmax>
      <ymax>229</ymax>
    </bndbox>
  </object>
  <object>
    <name>0</name>
    <pose>Unspecified</pose>
    <truncated>0</truncated>
    <difficult>0</difficult>
    <bndbox>
      <xmin>247</xmin>
      <ymin>194</ymin>
      <xmax>264</xmax>
      <ymax>233</ymax>
    </bndbox>
  </object>
  <object>
    <name>6</name>
    <pose>Unspecified</pose>
    <truncated>0</truncated>
    <difficult>0</difficult>
    <bndbox>
      <xmin>266</xmin>
      <ymin>196</ymin>
      <xmax>283</xmax>
      <ymax>231</ymax>
    </bndbox>
  </object>
  <object>
    <name>R</name>
    <pose>Unspecified</pose>
    <truncated>0</truncated>
    <difficult>0</difficult>
    <bndbox>
      <xmin>284</xmin>
      <ymin>196</ymin>
      <xmax>302</xmax>
      <ymax>232</ymax>
    </bndbox>
  </object>
  <object>
    <name>T</name>
    <pose>Unspecified</pose>
    <truncated>0</truncated>
    <difficult>0</difficult>
    <bndbox>
      <xmin>303</xmin>
      <ymin>196</ymin>
      <xmax>321</xmax>
      <ymax>231</ymax>
    </bndbox>
  </object>
  <object>
    <name>plate</name>
    <pose>Unspecified</pose>
    <truncated>0</truncated>
    <difficult>0</difficult>
    <bndbox>
      <xmin>153</xmin>
      <ymin>173</ymin>
      <xmax>353</xmax>
      <ymax>249</ymax>
    </bndbox>
  </object>
</annotation>
