

<annotation>
  <folder>JPEGImages</folder>
  <filename>1427</filename>
  <path>H:\labelImg-master\windows_v1.2.2\data\voc\VOCdevkit\VOC2019\JPEGImages\1427.jpg</path>
  <source>
    <database>Unknown</database></source>
  <size>
    <width>379</width>
    <height>299</height>
    <depth>"3"</depth></size>
  <segmented>0</segmented>
  <object>
    <name>plate</name>
    <pose>Unspecified</pose>
    <truncated>0</truncated>
    <difficult>0</difficult>
    <bndbox>
      <xmin>89</xmin>
      <ymin>88</ymin>
      <xmax>284</xmax>
      <ymax>207</ymax></bndbox></object>
  <object>
    <name>D</name>
    <pose>Unspecified</pose>
    <truncated>0</truncated>
    <difficult>0</difficult>
    <bndbox>
      <xmin>140</xmin>
      <ymin>133</ymin>
      <xmax>158</xmax>
      <ymax>166</ymax></bndbox></object>
  <object>
    <name>5</name>
    <pose>Unspecified</pose>
    <truncated>0</truncated>
    <difficult>0</difficult>
    <bndbox>
      <xmin>203</xmin>
      <ymin>134</ymin>
      <xmax>223</xmax>
      <ymax>167</ymax></bndbox></object>
  <object>
    <name>9</name>
    <pose>Unspecified</pose>
    <truncated>0</truncated>
    <difficult>0</difficult>
    <bndbox>
      <xmin>223</xmin>
      <ymin>135</ymin>
      <xmax>241</xmax>
      <ymax>167</ymax></bndbox></object>
  <object>
    <name>8</name>
    <pose>Unspecified</pose>
    <truncated>0</truncated>
    <difficult>0</difficult>
    <bndbox>
      <xmin>166</xmin>
      <ymin>133</ymin>
      <xmax>183</xmax>
      <ymax>166</ymax></bndbox></object>
  <object>
    <name>&#40657;</name>
    <pose>Unspecified</pose>
    <truncated>0</truncated>
    <difficult>0</difficult>
    <bndbox>
      <xmin>121</xmin>
      <ymin>132</ymin>
      <xmax>139</xmax>
      <ymax>167</ymax></bndbox></object>
  <object>
    <name>8</name>
    <pose>Unspecified</pose>
    <truncated>0</truncated>
    <difficult>0</difficult>
    <bndbox>
      <xmin>242</xmin>
      <ymin>136</ymin>
      <xmax>260</xmax>
      <ymax>168</ymax></bndbox></object>
  <object>
    <name>7</name>
    <pose>Unspecified</pose>
    <truncated>0</truncated>
    <difficult>0</difficult>
    <bndbox>
      <xmin>184</xmin>
      <ymin>133</ymin>
      <xmax>201</xmax>
      <ymax>166</ymax></bndbox></object></annotation>

