

<annotation>
  <folder>JPEGImages</folder>
  <filename>1964</filename>
  <path>H:\labelImg-master\windows_v1.2.2\data\voc\VOCdevkit\VOC2019\Train\1964.jpg</path>
  <source>
    <database>Unknown</database></source>
  <size>
    <width>281</width>
    <height>216</height>
    <depth>"3"</depth></size>
  <segmented>0</segmented>
  <object>
    <name>plate</name>
    <pose>Unspecified</pose>
    <truncated>0</truncated>
    <difficult>0</difficult>
    <bndbox>
      <xmin>70</xmin>
      <ymin>66</ymin>
      <xmax>217</xmax>
      <ymax>148</ymax></bndbox></object>
  <object>
    <name>X</name>
    <pose>Unspecified</pose>
    <truncated>0</truncated>
    <difficult>0</difficult>
    <bndbox>
      <xmin>106</xmin>
      <ymin>97</ymin>
      <xmax>119</xmax>
      <ymax>120</ymax></bndbox></object>
  <object>
    <name>&#24029;</name>
    <pose>Unspecified</pose>
    <truncated>0</truncated>
    <difficult>0</difficult>
    <bndbox>
      <xmin>94</xmin>
      <ymin>97</ymin>
      <xmax>106</xmax>
      <ymax>120</ymax></bndbox></object>
  <object>
    <name>G</name>
    <pose>Unspecified</pose>
    <truncated>0</truncated>
    <difficult>0</difficult>
    <bndbox>
      <xmin>125</xmin>
      <ymin>97</ymin>
      <xmax>138</xmax>
      <ymax>119</ymax></bndbox></object>
  <object>
    <name>5</name>
    <pose>Unspecified</pose>
    <truncated>0</truncated>
    <difficult>0</difficult>
    <bndbox>
      <xmin>138</xmin>
      <ymin>97</ymin>
      <xmax>151</xmax>
      <ymax>121</ymax></bndbox></object>
  <object>
    <name>8</name>
    <pose>Unspecified</pose>
    <truncated>0</truncated>
    <difficult>0</difficult>
    <bndbox>
      <xmin>179</xmin>
      <ymin>97</ymin>
      <xmax>192</xmax>
      <ymax>120</ymax></bndbox></object>
  <object>
    <name>2</name>
    <pose>Unspecified</pose>
    <truncated>0</truncated>
    <difficult>0</difficult>
    <bndbox>
      <xmin>152</xmin>
      <ymin>97</ymin>
      <xmax>165</xmax>
      <ymax>120</ymax></bndbox></object>
  <object>
    <name>5</name>
    <pose>Unspecified</pose>
    <truncated>0</truncated>
    <difficult>0</difficult>
    <bndbox>
      <xmin>166</xmin>
      <ymin>97</ymin>
      <xmax>179</xmax>
      <ymax>120</ymax></bndbox></object></annotation>

