

<annotation>
  <folder>JPEGImages</folder>
  <filename>3575</filename>
  <path>H:\labelImg-master\windows_v1.2.2\data\voc\VOCdevkit\VOC2019\Train\3575.jpg</path>
  <source>
    <database>Unknown</database></source>
  <size>
    <width>256</width>
    <height>186</height>
    <depth>"3"</depth></size>
  <segmented>0</segmented>
  <object>
    <name>plate</name>
    <pose>Unspecified</pose>
    <truncated>0</truncated>
    <difficult>0</difficult>
    <bndbox>
      <xmin>48</xmin>
      <ymin>35</ymin>
      <xmax>213</xmax>
      <ymax>148</ymax></bndbox></object>
  <object>
    <name>F</name>
    <pose>Unspecified</pose>
    <truncated>0</truncated>
    <difficult>0</difficult>
    <bndbox>
      <xmin>88</xmin>
      <ymin>78</ymin>
      <xmax>104</xmax>
      <ymax>107</ymax></bndbox></object>
  <object>
    <name>1</name>
    <pose>Unspecified</pose>
    <truncated>0</truncated>
    <difficult>0</difficult>
    <bndbox>
      <xmin>113</xmin>
      <ymin>78</ymin>
      <xmax>126</xmax>
      <ymax>108</ymax></bndbox></object>
  <object>
    <name>0</name>
    <pose>Unspecified</pose>
    <truncated>0</truncated>
    <difficult>0</difficult>
    <bndbox>
      <xmin>180</xmin>
      <ymin>80</ymin>
      <xmax>196</xmax>
      <ymax>109</ymax></bndbox></object>
  <object>
    <name>&#36195;</name>
    <pose>Unspecified</pose>
    <truncated>0</truncated>
    <difficult>0</difficult>
    <bndbox>
      <xmin>72</xmin>
      <ymin>77</ymin>
      <xmax>87</xmax>
      <ymax>107</ymax></bndbox></object>
  <object>
    <name>1</name>
    <pose>Unspecified</pose>
    <truncated>0</truncated>
    <difficult>0</difficult>
    <bndbox>
      <xmin>147</xmin>
      <ymin>79</ymin>
      <xmax>160</xmax>
      <ymax>108</ymax></bndbox></object>
  <object>
    <name>8</name>
    <pose>Unspecified</pose>
    <truncated>0</truncated>
    <difficult>0</difficult>
    <bndbox>
      <xmin>163</xmin>
      <ymin>79</ymin>
      <xmax>178</xmax>
      <ymax>108</ymax></bndbox></object>
  <object>
    <name>9</name>
    <pose>Unspecified</pose>
    <truncated>0</truncated>
    <difficult>0</difficult>
    <bndbox>
      <xmin>129</xmin>
      <ymin>79</ymin>
      <xmax>144</xmax>
      <ymax>107</ymax></bndbox></object></annotation>

