

<annotation>
  <folder>JPEGImages</folder>
  <filename>4680</filename>
  <path>H:\labelImg-master\windows_v1.2.2\data\voc\VOCdevkit\VOC2019\Val\4680.jpg</path>
  <source>
    <database>Unknown</database></source>
  <size>
    <width>341</width>
    <height>263</height>
    <depth>"3"</depth></size>
  <segmented>0</segmented>
  <object>
    <name>plate</name>
    <pose>Unspecified</pose>
    <truncated>0</truncated>
    <difficult>0</difficult>
    <bndbox>
      <xmin>79</xmin>
      <ymin>73</ymin>
      <xmax>269</xmax>
      <ymax>189</ymax></bndbox></object>
  <object>
    <name>V</name>
    <pose>Unspecified</pose>
    <truncated>0</truncated>
    <difficult>0</difficult>
    <bndbox>
      <xmin>147</xmin>
      <ymin>116</ymin>
      <xmax>164</xmax>
      <ymax>148</ymax></bndbox></object>
  <object>
    <name>&#28248;</name>
    <pose>Unspecified</pose>
    <truncated>0</truncated>
    <difficult>0</difficult>
    <bndbox>
      <xmin>109</xmin>
      <ymin>116</ymin>
      <xmax>123</xmax>
      <ymax>147</ymax></bndbox></object>
  <object>
    <name>1</name>
    <pose>Unspecified</pose>
    <truncated>0</truncated>
    <difficult>0</difficult>
    <bndbox>
      <xmin>204</xmin>
      <ymin>118</ymin>
      <xmax>218</xmax>
      <ymax>149</ymax></bndbox></object>
  <object>
    <name>D</name>
    <pose>Unspecified</pose>
    <truncated>0</truncated>
    <difficult>0</difficult>
    <bndbox>
      <xmin>165</xmin>
      <ymin>117</ymin>
      <xmax>183</xmax>
      <ymax>149</ymax></bndbox></object>
  <object>
    <name>8</name>
    <pose>Unspecified</pose>
    <truncated>0</truncated>
    <difficult>0</difficult>
    <bndbox>
      <xmin>220</xmin>
      <ymin>119</ymin>
      <xmax>237</xmax>
      <ymax>149</ymax></bndbox></object>
  <object>
    <name>M</name>
    <pose>Unspecified</pose>
    <truncated>0</truncated>
    <difficult>0</difficult>
    <bndbox>
      <xmin>123</xmin>
      <ymin>116</ymin>
      <xmax>139</xmax>
      <ymax>147</ymax></bndbox></object>
  <object>
    <name>5</name>
    <pose>Unspecified</pose>
    <truncated>0</truncated>
    <difficult>0</difficult>
    <bndbox>
      <xmin>184</xmin>
      <ymin>117</ymin>
      <xmax>201</xmax>
      <ymax>149</ymax></bndbox></object></annotation>

